collect_static/__init__.py
collect_static/collect.py
collect_static-0.1.1.dist-info/METADATA
collect_static-0.1.1.dist-info/WHEEL
collect_static-0.1.1.dist-info/entry_points.txt
collect_static-0.1.1.dist-info/RECORD
