Metadata-Version: 2.1
Name: collect_static
Version: 0.1.1
Summary: Provides APIs to collect/copy files to destination directory by file name pattern from given directories in script dir
License: Apache-2.0
Author: Avinash Gowda
Author-email: avinashgowda.1994@gmail.com
Requires-Python: >=3.10,<4.0
Classifier: License :: OSI Approved :: Apache Software License
Classifier: Programming Language :: Python :: 3
Classifier: Programming Language :: Python :: 3.10
Classifier: Programming Language :: Python :: 3.11
Classifier: Programming Language :: Python :: 3.12
Requires-Dist: click (>=8.1.7,<9.0.0)
Requires-Dist: tqdm (>=4.66.5,<5.0.0)
